{"cameraMode":{"drawMode":0,"name":"Shaded","section":"Shading Mode"},"sceneLighting":true,"audioPlay":false,"sceneViewState":{"showFog":true,"showMaterialUpdate":false,"showSkybox":true,"showFlares":true,"showImageEffects":true,"showParticleSystems":true},"in2DMode":false,"pivot":{"x":-6.165403366088867,"y":5.029433727264404,"z":0.44517993927001955},"rotation":{"x":-0.15021689236164094,"y":-0.384118914604187,"z":0.06347685307264328,"w":-0.9087677001953125},"size":7.871785640716553,"orthographic":false}